gd_sm/__init__.py
gd_sm/_sm2.py
gd_sm/sm2.py
gd_sm/sm3.py
gd_sm/sm4.py
gd_sm/test/__init__.py
gd_sm/test/example.py
gd_sm/test/test.py
gd_sm-1.0.6.dist-info/WHEEL
gd_sm-1.0.6.dist-info/METADATA
gd_sm-1.0.6.dist-info/RECORD
