Metadata-Version: 2.4
Name: gd_sm
Version: 1.0.6
Summary: python实现的国密SM2/SM3/SM4算法库
Author-email: liudi <di.liu@quantum-info.com>
Requires-Dist: cryptography >=35.0.2
Project-URL: Home, https://www.quantumtest.top
